band_gap_ml/__init__.py
band_gap_ml/band_gap_predictor.py
band_gap_ml/config.py
band_gap_ml/model_training.py
band_gap_ml/vectorizer.py
band_gap_ml/data/elements.csv
band_gap_ml/data/train_classification.csv
band_gap_ml/data/train_regression.csv
bandgap_ml-1.3.dist-info/LICENSE.md
bandgap_ml-1.3.dist-info/METADATA
bandgap_ml-1.3.dist-info/WHEEL
bandgap_ml-1.3.dist-info/top_level.txt
bandgap_ml-1.3.dist-info/RECORD
