Metadata-Version: 2.2
Name: BandGap-ml
Version: 1.3
Summary: Project for predicting band gaps of inorganic materials by using ML models
Home-page: https://github.com/alexey-krasnov/BandGap-ml
Author: Dr.Aleksei Krasnov
Author-email: alexeykrasnov1989@gmail.com
License: MIT
Classifier: Topic :: Software Development :: Build Tools
Classifier: License :: OSI Approved :: MIT License
Classifier: Programming Language :: Python :: 3
Classifier: Programming Language :: Python :: 3.9
Classifier: Programming Language :: Python :: 3.10
Classifier: Programming Language :: Python :: 3.11
Classifier: Programming Language :: Python :: 3.12
Requires-Python: >=3.10,<3.13
License-File: LICENSE.md
Requires-Dist: numpy>=1.26.3
Requires-Dist: pandas>=2.2.0
Requires-Dist: scikit-learn>=1.3.2
Requires-Dist: openpyxl>=3.1.5
Requires-Dist: streamlit>=1.38.0
Requires-Dist: streamlit-navigation-bar
Requires-Dist: streamlit_extras
Requires-Dist: streamlit-toggle-switch
Requires-Dist: pymatgen>=2024.10.3
Requires-Dist: xgboost>=2.1.4
Dynamic: author
Dynamic: author-email
Dynamic: classifier
Dynamic: description
Dynamic: description-content-type
Dynamic: home-page
Dynamic: license
Dynamic: requires-dist
Dynamic: requires-python
Dynamic: summary
